hindi_stopwords/__init__.py
hindi_stopwords/stopwords.py
hindi_stopwords-0.1.0.dist-info/METADATA
hindi_stopwords-0.1.0.dist-info/WHEEL
hindi_stopwords-0.1.0.dist-info/top_level.txt
hindi_stopwords-0.1.0.dist-info/RECORD
